aurora_dsql_asyncpg/__init__.py
aurora_dsql_asyncpg/connector.py
aurora_dsql_asyncpg/pool.py
aurora_dsql_psycopg/__init__.py
aurora_dsql_psycopg/connection_class.py
aurora_dsql_psycopg2/__init__.py
aurora_dsql_psycopg2/connector.py
aurora_dsql_psycopg2/pool.py
aurora_dsql_python_connector-0.2.2.dist-info/licenses/LICENSE
aurora_dsql_python_connector-0.2.2.dist-info/licenses/NOTICE
dsql_core/connection_properties.py
dsql_core/connection_utils.py
dsql_core/token_manager.py
aurora_dsql_python_connector-0.2.2.dist-info/METADATA
aurora_dsql_python_connector-0.2.2.dist-info/WHEEL
aurora_dsql_python_connector-0.2.2.dist-info/top_level.txt
aurora_dsql_python_connector-0.2.2.dist-info/RECORD
