Metadata-Version: 2.4
Name: aurora-dsql-python-connector
Version: 0.2.2
Summary: A connector that integrates IAM Authentication for connecting Python applications to Amazon Aurora DSQL clusters
Author-email: Amazon Web Services <aws-aurora-dsql-feedback@amazon.com>
License-Expression: Apache-2.0
Project-URL: Homepage, https://github.com/awslabs/aurora-dsql-python-connector
Project-URL: Repository, https://github.com/awslabs/aurora-dsql-python-connector
Project-URL: Documentation, https://github.com/awslabs/aurora-dsql-python-connector
Project-URL: Bug Tracker, https://github.com/awslabs/aurora-dsql-python-connector/issues
Classifier: Intended Audience :: Developers
Classifier: Programming Language :: Python
Classifier: Programming Language :: Python :: 3.10
Classifier: Programming Language :: Python :: 3.11
Classifier: Programming Language :: Python :: 3.12
Classifier: Programming Language :: Python :: 3.13
Requires-Python: >=3.10
License-File: LICENSE
License-File: NOTICE
Requires-Dist: boto3>=1.35.74
Provides-Extra: psycopg
Requires-Dist: psycopg[binary]>=3.1.0; extra == "psycopg"
Requires-Dist: psycopg-pool>=3.2.6; extra == "psycopg"
Provides-Extra: psycopg2
Requires-Dist: psycopg2-binary>=2.9.0; extra == "psycopg2"
Provides-Extra: asyncpg
Requires-Dist: asyncpg>=0.30.0; extra == "asyncpg"
Provides-Extra: dev
Requires-Dist: pytest>=8.0; extra == "dev"
Requires-Dist: pytest-cov>=4.0.0; extra == "dev"
Requires-Dist: pytest-asyncio>=1.2.0; extra == "dev"
Requires-Dist: black>=23.0.0; extra == "dev"
Requires-Dist: flake8>=6.0.0; extra == "dev"
Requires-Dist: mypy>=1.0.0; extra == "dev"
Requires-Dist: isort>=7.0.0; extra == "dev"
Dynamic: license-file
